xlineparse/__init__.py
xlineparse/py.typed
xlineparse/xlineparse.cpython-311-darwin.so
xlineparse-0.0.6.dist-info/RECORD
xlineparse-0.0.6.dist-info/WHEEL
xlineparse-0.0.6.dist-info/entry_points.txt
xlineparse-0.0.6.dist-info/METADATA
xlineparse-0.0.6.dist-info/license_files/LICENSE
