Metadata-Version: 2.3
Name: xlineparse
Version: 0.0.6
Classifier: Programming Language :: Python
Requires-Dist: maturin ==1.4.0 ; extra == 'dev'
Requires-Dist: pytest ==7.* ; extra == 'dev'
Requires-Dist: mypy ==1.6.* ; extra == 'dev'
Requires-Dist: pip ==24.0 ; extra == 'dev'
Requires-Dist: pytest ==7.* ; extra == 'test'
Provides-Extra: dev
Provides-Extra: test
License-File: LICENSE
Summary: Parse variable length delimited lines
Keywords: diff
Author: Oliver Russell <ojhrussell@gmail.com>
Author-email: Oliver Russell <ojhrussell@gmail.com>
Maintainer-email: Oliver Russell <ojhrussell@gmail.com>
Requires-Python: >=3.10
Project-URL: homepage, https://github.com/leontrolski/xlineparse
Project-URL: documentation, https://github.com/leontrolski/xlineparse
Project-URL: repository, https://github.com/leontrolski/xlineparse.git
